{
  "users": [
    {
      "email": "magih@mailinator.com",
      "password": "$2a$10$2ZZoheVC5Q.fSKpxDgti0OX6xevQ7VSn0hAqnrFFKo5CG1dp8b9QW",
      "id": 1
    },
    {
      "email": "qodaquru@mailinator.com",
      "password": "$2a$10$ct72GRCcoQtwCxTHggwqKOYyuDKO3TjVuLAo0MKsTHHC79aoSFuKK",
      "id": 3
    },
    {
      "email": "sogulegeh@mailinator.com",
      "password": "$2a$10$5Tx69a4VufvGJPb6fthX4eWadQ9TjAfD2E8t1k70WNoW7KLaD3wq6",
      "id": 4
    },
    {
      "email": "fuad@gmail.com",
      "password": "$2a$10$yuCj1uhvtxFAgm0ELXKYreJjaejV137kHcXEwv9M7AqiAIZGWDrrq",
      "id": 5
    }
  ],
  "blogs": [
    {
      "userId": 5,
      "author": "fuad@gmail.com",
      "judul": "Pantai Pasir Panjang",
      "img": "https://images.pexels.com/photos/10866644/pexels-photo-10866644.jpeg?auto=compress&cs=tinysrgb&w=600&lazy=load",
      "content": "Liburan akhir tahun",
      "createdAt": "9/21/2022",
      "id": 1
    },
    {
      "userId": 5,
      "author": "fuad@gmail.com",
      "judul": "Air terjun ok",
      "img": "https://images.pexels.com/photos/4534200/pexels-photo-4534200.jpeg?auto=compress&cs=tinysrgb&w=1260&h=750&dpr=1",
      "content": "Rerum reiciendis exe",
      "createdAt": "9/21/2022",
      "id": 2
    }
  ]
}